__init__.py
pymeddra/__init__.py
pymeddra/parse.py
pymeddra/tree.py
pymeddra-0.0.6.dist-info/LICENSE
pymeddra-0.0.6.dist-info/METADATA
pymeddra-0.0.6.dist-info/WHEEL
pymeddra-0.0.6.dist-info/top_level.txt
pymeddra-0.0.6.dist-info/RECORD
