Metadata-Version: 2.1
Name: pymeddra
Version: 0.0.6
Summary: Parse and use MedDRA in Python.
Author-email: Karel D'Oosterlinck <kareldoosterlinck@gmail.com>
Project-URL: Homepage, https://github.com/KarelDO/pymeddra
Project-URL: Bug Tracker, https://github.com/KarelDO/pymeddra/issues
Classifier: Programming Language :: Python :: 3
Classifier: License :: OSI Approved :: MIT License
Classifier: Operating System :: OS Independent
Requires-Python: >=3.9
License-File: LICENSE
Requires-Dist: pydantic (>=1.10.4)
